anki_slicer/__init__.py
anki_slicer/__main__.py
anki_slicer/ankiconnect.py
anki_slicer/config.py
anki_slicer/exporter.py
anki_slicer/main.py
anki_slicer/player.py
anki_slicer/segment_adjuster.py
anki_slicer/slicer.py
anki_slicer/subs.py
anki_slicer/ui.py
anki_slicer-0.3.1.dist-info/licenses/LICENSE
anki_slicer-0.3.1.dist-info/METADATA
anki_slicer-0.3.1.dist-info/WHEEL
anki_slicer-0.3.1.dist-info/entry_points.txt
anki_slicer-0.3.1.dist-info/top_level.txt
anki_slicer-0.3.1.dist-info/RECORD
