Metadata-Version: 2.4
Name: anki-slicer
Version: 0.3.1
Summary: Slice audio + subtitles and export to Anki via AnkiConnect
Author-email: Lee Hunter <you@example.com>
License: MIT
Project-URL: Homepage, https://github.com/leehunter/anki-slicer
Project-URL: Issues, https://github.com/leehunter/anki-slicer/issues
Requires-Python: >=3.9
License-File: LICENSE
Requires-Dist: pydub>=0.25.1
Requires-Dist: PyQt6>=6.6.0
Requires-Dist: requests>=2.31.0
Requires-Dist: numpy>=1.26.0
Requires-Dist: matplotlib>=3.7.0
Dynamic: license-file
